csw/AlarmService.py
csw/Cancellable.py
csw/CommandResponse.py
csw/CommandResponseManager.py
csw/CommandServer.py
csw/CommandService.py
csw/CommandServiceRequest.py
csw/ComponentHandlers.py
csw/ConfigService.py
csw/CoordinateSystem.py
csw/Coords.py
csw/CurrentState.py
csw/EnumUtil.py
csw/Event.py
csw/EventKey.py
csw/EventName.py
csw/EventPublisher.py
csw/EventService.py
csw/EventSubscriber.py
csw/EventSubscription.py
csw/EventTime.py
csw/ExposureId.py
csw/ExposureNumber.py
csw/KeyTypes.py
csw/LocationService.py
csw/LocationServiceSync.py
csw/ObsId.py
csw/ObserveEventKeys.py
csw/ObserveEventNames.py
csw/OperationalState.py
csw/ParamFactories.py
csw/Parameter.py
csw/ParameterSetType.py
csw/Prefix.py
csw/ProgramId.py
csw/RedisConnector.py
csw/SemesterId.py
csw/Separator.py
csw/SequencerCommandService.py
csw/SequencerObserveEvent.py
csw/Subsystem.py
csw/TMTTime.py
csw/TYPLevel.py
csw/TimeServiceScheduler.py
csw/Units.py
csw/__init__.py
esw/EswSequencerResponse.py
esw/ObsMode.py
esw/Sequence.py
esw/SequencerClient.py
esw/SequencerRequest.py
esw/SequencerServer.py
esw/Step.py
esw/StepList.py
esw/StepStatus.py
esw/Variation.py
esw/WsCommands.py
esw/__init__.py
esw/esw-shell.py
tmtpycsw-6.0.0.dist-info/licenses/LICENSE
tmtpycsw-6.0.0.dist-info/METADATA
tmtpycsw-6.0.0.dist-info/WHEEL
tmtpycsw-6.0.0.dist-info/top_level.txt
tmtpycsw-6.0.0.dist-info/RECORD
