Metadata-Version: 2.4
Name: tmtpycsw
Version: 6.0.0
Summary: A python API for TMT CSW services
Home-page: https://github.com/tmtsoftware/csw-python
Author: Allan Brighton
Author-email: abrighton@tmt.org
Classifier: Programming Language :: Python :: 3
Classifier: License :: OSI Approved :: MIT License
Classifier: Operating System :: OS Independent
Requires-Python: >=3.13
License-File: LICENSE
Dynamic: author
Dynamic: author-email
Dynamic: classifier
Dynamic: description
Dynamic: description-content-type
Dynamic: home-page
Dynamic: license-file
Dynamic: requires-python
Dynamic: summary
